TigerPackage/__init__.py
TigerPackage/divide_by_three.py
divide/__init__.py
divide/divide_by_three.py
TigerPackage-1.0.1.dist-info/License
TigerPackage-1.0.1.dist-info/METADATA
TigerPackage-1.0.1.dist-info/WHEEL
TigerPackage-1.0.1.dist-info/top_level.txt
TigerPackage-1.0.1.dist-info/RECORD
