Metadata-Version: 2.1
Name: TigerPackage
Version: 1.0.1
Summary: Full package for TigerResort
Home-page: https://github.com/gmyrianthous/example-publish-pypi
Author: ShihTing Yen
Author-email: bafortingbin@gmail.com
License: MIT
Classifier: Programming Language :: Python :: 3.7
Classifier: Programming Language :: Python :: 3.8
Classifier: Programming Language :: Python :: 3.9
Classifier: Programming Language :: Python :: 3.10
Classifier: Programming Language :: Python :: 3.11
Requires-Python: >=3.7
License-File: License
